x2s3/__init__.py
x2s3/app.py
x2s3/client.py
x2s3/client_aioboto.py
x2s3/client_file.py
x2s3/client_registry.py
x2s3/settings.py
x2s3/utils.py
x2s3-1.1.0.dist-info/licenses/LICENSE
x2s3-1.1.0.dist-info/METADATA
x2s3-1.1.0.dist-info/WHEEL
x2s3-1.1.0.dist-info/top_level.txt
x2s3-1.1.0.dist-info/RECORD
