Metadata-Version: 2.4
Name: x2s3
Version: 1.1.0
Summary: RESTful web service which makes any storage system X available as an S3-compatible REST API
Author-email: Konrad Rokicki <rokicki@janelia.hhmi.org>
License: BSD 3-Clause License
Project-URL: Homepage, https://github.com/JaneliaSciComp/x2s3
Project-URL: Repository, https://github.com/JaneliaSciComp/x2s3
Classifier: License :: OSI Approved :: BSD License
Classifier: Operating System :: OS Independent
Classifier: Programming Language :: Python :: 3
Classifier: Intended Audience :: Science/Research
Classifier: Operating System :: OS Independent
Classifier: Topic :: Software Development :: Libraries :: Python Modules
Requires-Python: >=3.12
License-File: LICENSE
Requires-Dist: aiobotocore>=2.22
Requires-Dist: boto3>=1.37
Requires-Dist: botocore>=1.37
Requires-Dist: fastapi>=0.115
Requires-Dist: loguru>=0.7
Requires-Dist: pydantic>=2.11
Requires-Dist: pydantic-settings>=2.9
Requires-Dist: pydantic-settings-yaml>=0.2.0
Requires-Dist: python-dateutil>=2.9
Requires-Dist: pytest>=8.3
Requires-Dist: starlette>=0.46
Requires-Dist: uvicorn>=0.34
Requires-Dist: uvloop>=0.21
Requires-Dist: jinja2>=3.1
Provides-Extra: test
Requires-Dist: pytest; extra == "test"
Requires-Dist: pytest-cov; extra == "test"
Requires-Dist: pytest-html; extra == "test"
Requires-Dist: httpx>=0.28; extra == "test"
Provides-Extra: release
Requires-Dist: build; extra == "release"
Requires-Dist: twine; extra == "release"
Dynamic: license-file
